.DS_Store
hotWater/EDTSurf
hotWater/__init__.py
hotWater/atom_type.py
hotWater/h2o_bind.py
hotWater/model.py
hotWater/water_hot_spots_adv_new.h5
hot_water/__init__.py
hot_water/atom_type.py
hot_water/h2o_bind.py
hot_water/model.py
hotWater-3.3.dist-info/LICENSE.txt
hotWater-3.3.dist-info/METADATA
hotWater-3.3.dist-info/WHEEL
hotWater-3.3.dist-info/dependency_links.txt
hotWater-3.3.dist-info/top_level.txt
hotWater-3.3.dist-info/RECORD
