Metadata-Version: 2.1
Name: hotWater
Version: 3.3
Summary: The program uses a residual deep learning model to predict water hot-spots on the surface of proteins
Home-page: UNKNOWN
Author: Jan Zaucha
Author-email: trelek2@gmail.com
License: MIT
Platform: UNKNOWN
Requires-Dist: numpy
Requires-Dist: scipy
Requires-Dist: biopython (==1.74)
Requires-Dist: matplotlib
Requires-Dist: scikit-learn
Requires-Dist: tensorflow
Requires-Dist: tensorflow-gpu
Requires-Dist: keras (==2.3.1)
Requires-Dist: neural-structured-learning
